LICENSE
MANIFEST.in
README.md
setup.cfg
setup.py
gists.cli.py3.egg-info/PKG-INFO
gists.cli.py3.egg-info/SOURCES.txt
gists.cli.py3.egg-info/dependency_links.txt
gists.cli.py3.egg-info/entry_points.txt
gists.cli.py3.egg-info/requires.txt
gists.cli.py3.egg-info/top_level.txt
gists_cli/__init__.py
gists_cli/actions.py
gists_cli/api.py
gists_cli/defaults.py
gists_cli/gists.py
gists_cli/log.py
gists_cli/util.py